Metadata-Version: 2.4
Name: codon-jit
Version: 0.4.3
Summary: Codon JIT decorator
Home-page: https://exaloop.io
Author: Exaloop Inc.
Author-email: info@exaloop.io
License: Apache License 2.0
Requires-Python: >=3.6
Requires-Dist: cython
Requires-Dist: astunparse
Dynamic: author
Dynamic: author-email
Dynamic: description
Dynamic: home-page
Dynamic: license
Dynamic: requires-dist
Dynamic: requires-python
Dynamic: summary
